{
    "products": [
        {
            "id": 1,
            "image": [
                {
                    "url": "./assets/whale2.png"
                }
            ],
            "name": "Blue Whale",
            "price": "999999",
            "category": 1
        },
        {
            "id": 2,
            "image": [
                {
                    "url": "./assets/whale.png"
                }
            ],
            "name": "White Whale",
            "price": "988888",
            "category": 1
        },
        {
            "id": 3,
            "image": [
                {
                    "url": "./assets/stopwatch.png"
                }
            ],
            "name": "Stop Watch",
            "price": "123456",
            "category": 2
        }
    ],
    "categories": [
        {
            "id": 1,
            "name": "Đồng hồ",
            "image": [
                {
                    "source": "C:/Users/Tuani/MyBlankRnApp/assets/stopwatch.png"
                }
            ]
        },
        {
            "id": 2,
            "name": "Cá Voi",
            "image": "Whale"
        },
        {
            "id": 3,
            "name": "Cá Voi Xanh",
            "image": "Whale2"
        }
    ]
}